hitchprojectsync/__init__.py
hitchprojectsync/app.py
hitchprojectsync-0.1.0.dist-info/LICENSE.txt
hitchprojectsync-0.1.0.dist-info/METADATA
hitchprojectsync-0.1.0.dist-info/WHEEL
hitchprojectsync-0.1.0.dist-info/entry_points.txt
hitchprojectsync-0.1.0.dist-info/top_level.txt
hitchprojectsync-0.1.0.dist-info/RECORD
